<?xml version="1.0" encoding="UTF-8"?>
<!DOCTYPE mapper PUBLIC "-//mybatis.org//DTD Mapper 3.0//EN" "http://mybatis.org/dtd/mybatis-3-mapper.dtd">
<mapper namespace="org.shjr.iplat.mybatis.generator.dao.SysRoleMapper">
  <resultMap id="BaseResultMap" type="org.shjr.iplat.mybatis.generator.model.SysRole">
    <!--
      WARNING - @mbggenerated
      This element is automatically generated by MyBatis Generator, do not modify.
    -->
    <id column="id" jdbcType="INTEGER" property="id" />
    <result column="role_name" jdbcType="VARCHAR" property="roleName" />
    <result column="dept_id" jdbcType="INTEGER" property="deptId" />
    <result column="role_type" jdbcType="INTEGER" property="roleType" />
    <result column="enable" jdbcType="INTEGER" property="enable" />
    <result column="remark" jdbcType="VARCHAR" property="remark" />
  </resultMap>
  <delete id="deleteByPrimaryKey" parameterType="java.lang.Integer">
    <!--
      WARNING - @mbggenerated
      This element is automatically generated by MyBatis Generator, do not modify.
    -->
    delete from sys_role
    where id = #{id,jdbcType=INTEGER}
  </delete>
  <insert id="insert" keyProperty="id" parameterType="org.shjr.iplat.mybatis.generator.model.SysRole" useGeneratedKeys="true">
    <!--
      WARNING - @mbggenerated
      This element is automatically generated by MyBatis Generator, do not modify.
    -->
    insert into sys_role (role_name, dept_id, role_type, 
      enable, remark)
    values (#{roleName,jdbcType=VARCHAR}, #{deptId,jdbcType=INTEGER}, #{roleType,jdbcType=INTEGER}, 
      #{enable,jdbcType=INTEGER}, #{remark,jdbcType=VARCHAR})
  </insert>
  <update id="updateByPrimaryKey" parameterType="org.shjr.iplat.mybatis.generator.model.SysRole">
    <!--
      WARNING - @mbggenerated
      This element is automatically generated by MyBatis Generator, do not modify.
    -->
    update sys_role
    set role_name = #{roleName,jdbcType=VARCHAR},
      dept_id = #{deptId,jdbcType=INTEGER},
      role_type = #{roleType,jdbcType=INTEGER},
      enable = #{enable,jdbcType=INTEGER},
      remark = #{remark,jdbcType=VARCHAR}
    where id = #{id,jdbcType=INTEGER}
  </update>
  <select id="selectByPrimaryKey" parameterType="java.lang.Integer" resultMap="BaseResultMap">
    <!--
      WARNING - @mbggenerated
      This element is automatically generated by MyBatis Generator, do not modify.
    -->
    select id, role_name, dept_id, role_type, enable, remark
    from sys_role
    where id = #{id,jdbcType=INTEGER}
  </select>
  <select id="selectAll" resultMap="BaseResultMap">
    <!--
      WARNING - @mbggenerated
      This element is automatically generated by MyBatis Generator, do not modify.
    -->
    select id, role_name, dept_id, role_type, enable, remark
    from sys_role
  </select>
</mapper>